EE-CS-371-330-Computer-Architecture/Lab/Lab_5/CA_lab_counter/CA_lab_counter.srcs/sources_1/new/switches.v
module switches (
    input              clk,
    input              rst,
    input  [31:0]      writeData,
    input              writeEnable,
    input              readEnable,
    input  [29:0]      memAddress,
    output reg [31:0]  readData,
    output reg [15:0]  leds
);

    initial readData = 32'd0;

    always @(posedge clk) begin
        if (rst) begin
            leds <= 16'd0;
        end
    end

endmodule

EE-CS-371-330-Computer-Architecture/Lab/Lab_5/CA_lab_counter/CA_lab_counter.srcs/sources_1/new/leds.v
//Synchronises the raw slide-switch inputs into the
// FPGA clock domain using a two-flop synchroniser chain.
// This eliminates metastability when sampling asynchronous
// mechanical switch inputs at 100 MHz.
module leds (
    input              clk,
    input              rst,
    input  [15:0]      btns,
    input  [31:0]      writeData,
    input              writeEnable,
    input              readEnable,
    input  [29:0]      memAddress,
    input  [15:0]      switches,
    output reg [31:0]  readData
);

    reg [15:0] sync_stage1;

    always @(posedge clk) begin
        if (rst) begin
            sync_stage1      <= 16'd0;
            readData         <= 32'd0;
        end else begin
            sync_stage1      <= switches;
            readData[15:0]   <= sync_stage1;
            readData[31:16]  <= 16'd0;
        end
    end

endmodule

EE-CS-371-330-Computer-Architecture/Lab/Lab_5/CA_lab_counter/CA_lab_counter.srcs/sources_1/new/debouncer.v
//  Removes mechanical contact bounce from a
// pushbutton.  Uses a counter-based approach: the raw button
// signal must remain stable for STABLE_MAX consecutive clock
// cycles before the output is updated.

module debouncer #(
    parameter STABLE_MAX = 500_000
)(
    input  wire clk,
    input  wire pbin,
    output reg  pbout
);

    reg [$clog2(STABLE_MAX+1)-1 : 0] stable_cnt;
    reg prev_in;

    initial begin
        pbout      = 1'b0;
        prev_in    = 1'b0;
        stable_cnt = 0;
    end

    always @(posedge clk) begin
        if (pbin == prev_in) begin
            if (stable_cnt < STABLE_MAX) begin
                stable_cnt <= stable_cnt + 1;
            end else begin
                pbout <= prev_in;
            end
        end else begin
            prev_in    <= pbin;
            stable_cnt <= 0;
        end
    end

endmodule

EE-CS-371-330-Computer-Architecture/Lab/Lab_5/CA_lab_counter/CA_lab_counter.srcs/sources_1/new/clock_divider.v
//Divides the 100 MHz Basys3 system clock down
//  to a slow enable-pulse used by the FSM counter.

module clock_divider #(
    parameter MAX_COUNT = 25_000_000
)(
    input  wire clk,
    input  wire rst,
    output reg  slow_clk
);

    reg [$clog2(MAX_COUNT)-1 : 0] count;

    always @(posedge clk) begin
        if (rst) begin
            count    <= 0;
            slow_clk <= 1'b0;
        end else begin
            slow_clk <= 1'b0;
            if (count == MAX_COUNT - 1) begin
                count    <= 0;
                slow_clk <= 1'b1;
            end else begin
                count <= count + 1;
            end
        end
    end

endmodule

EE-CS-371-330-Computer-Architecture/Lab/Lab_5/CA_lab_counter/CA_lab_counter.srcs/sources_1/new/fsm_top.v
module fsm_top #(
    parameter CLK_DIV_MAX   = 25_000_000,
    parameter DEBOUNCE_STAB = 500_000
)(
    input  wire        clk,
    input  wire        btn_reset_raw,
    input  wire [15:0] sw_raw,
    output reg  [15:0] led_out
);

    wire        slow_clk;
    wire        btn_reset;
    wire [31:0] sw_synced_bus;
    wire [15:0] sw_synced;
    wire [31:0] led_module_readData_nc;

    clock_divider #(
        .MAX_COUNT(CLK_DIV_MAX)
    ) u_clkdiv (
        .clk      (clk),
        .rst      (1'b0),
        .slow_clk (slow_clk)
    );

    debouncer #(
        .STABLE_MAX(DEBOUNCE_STAB)
    ) u_debouncer (
        .clk   (clk),
        .pbin  (btn_reset_raw),
        .pbout (btn_reset)
    );

    leds u_switch_iface (
        .clk         (clk),
        .rst         (btn_reset),
        .btns        (16'd0),
        .writeData   (32'd0),
        .writeEnable (1'b0),
        .readEnable  (1'b1),
        .memAddress  (30'd0),
        .switches    (sw_raw),
        .readData    (sw_synced_bus)
    );

    assign sw_synced = sw_synced_bus[15:0];

    switches u_led_iface (
        .clk         (clk),
        .rst         (btn_reset),
        .writeData   (32'd0),
        .writeEnable (1'b0),
        .readEnable  (1'b0),
        .memAddress  (30'd0),
        .readData    (led_module_readData_nc),
        .leds        ()
    );

    localparam WAIT  = 1'b0;
    localparam COUNT = 1'b1;

    reg        state;
    reg [15:0] counter_reg;

    always @(posedge clk) begin
        if (btn_reset) begin
            state       <= WAIT;
            counter_reg <= 16'd0;
            led_out     <= 16'd0;
        end else begin
            case (state)

                WAIT: begin
                    led_out <= 16'd0;
                    if (sw_synced != 16'd0) begin
                        counter_reg <= sw_synced;
                        state       <= COUNT;
                    end
                end

                COUNT: begin
                    led_out <= counter_reg;
                    if (slow_clk) begin
                        if (counter_reg == 16'd1) begin
                            counter_reg <= 16'd0;
                            led_out     <= 16'd0;
                            state       <= WAIT;
                        end else begin
                            counter_reg <= counter_reg - 16'd1;
                        end
                    end
                end

                default: begin
                    state   <= WAIT;
                    led_out <= 16'd0;
                end
            endcase
        end
    end

endmodule

EE-CS-371-330-Computer-Architecture/Lab/Lab_5/CA_lab_counter/CA_lab_counter.srcs/sim_1/new/tb_fsm_top.v
// ============================================================
// Testbench: tb_fsm_top
// Lab 5 - Designing FSM Using FPGA Switches and LEDs
//
// COVERAGE:
//   Test 1 - Power-on idle:     switches = 0 ? LEDs must stay 0
//   Test 2 - Countdown from 7:  SW0+SW1+SW2 ? LEDs 7,6,5,4,3,2,1,0
//   Test 3 - Mid-count reset:   Press BTNC mid-countdown ? LEDs = 0
//   Test 4 - Countdown from 4:  SW2 only ? LEDs 4,3,2,1,0
//   Test 5 - Re-trigger after countdown completes naturally
//
// SIMULATION SPEED:
//   CLK_DIV_SIM = 5  ? slow_clk fires every 5 fast cycles.
//   DEBOUNCE_SIM = 3 ? debouncer accepts after 3 stable cycles.
//   This makes the entire sim finish in microseconds.
//
// HOW TO RUN (Vivado):
//   1. Add tb_fsm_top.v as simulation source
//   2. Set tb_fsm_top as the top simulation module
//   3. Run Behavioral Simulation
//   4. Observe $display output in Tcl console
//   5. Check waveforms: state, counter_reg, led_out, sw_raw
//
// PASS CRITERIA:
//   • No FAIL messages in the console output
//   • Waveform shows led_out counting down in binary
//   • led_out returns to 0 at end of each countdown
//   • led_out immediately becomes 0 when reset pressed
// ============================================================

`timescale 1ns / 1ps

module tb_fsm_top;

    // ??? Simulation parameters ????????????????????????????????
    localparam CLK_DIV_SIM   = 5;    // very small for fast sim
    localparam DEBOUNCE_SIM  = 3;    // fast debounce for sim
    // One slow_clk period in fast-clock cycles
    localparam SLOW_PERIOD   = CLK_DIV_SIM;

    // ??? DUT I/O ??????????????????????????????????????????????
    reg         clk;
    reg         btn_reset_raw;
    reg  [15:0] sw_raw;
    wire [15:0] led_out;

    // ??? Instantiate DUT with simulation parameters ???????????
    fsm_top #(
        .CLK_DIV_MAX  (CLK_DIV_SIM),
        .DEBOUNCE_STAB(DEBOUNCE_SIM)
    ) dut (
        .clk           (clk),
        .btn_reset_raw (btn_reset_raw),
        .sw_raw        (sw_raw),
        .led_out       (led_out)
    );

    // ??? 100 MHz clock: period = 10 ns ????????????????????????
    initial clk = 0;
    always  #5 clk = ~clk;

    // ??? Pass/Fail tracking ???????????????????????????????????
    integer pass_count = 0;
    integer fail_count = 0;

    // ??? Helper tasks ?????????????????????????????????????????

    // Wait N fast clock cycles
    task wait_cycles;
        input integer n;
        integer i;
        begin
            for (i = 0; i < n; i = i + 1)
                @(posedge clk);
        end
    endtask

    // Wait N slow_clk periods (each = SLOW_PERIOD fast cycles)
    task wait_slow;
        input integer n;
        begin
            wait_cycles(n * SLOW_PERIOD);
        end
    endtask

    // Check led_out equals expected value
    task check_led;
        input [15:0] expected;
        input [63:0] test_id;   // test number for messages
        begin
            @(posedge clk); // let signals settle
            #1;              // small delta delay
            if (led_out === expected) begin
                $display("  [PASS] Test %0d: led_out = %0d (0b%016b)",
                         test_id, led_out, led_out);
                pass_count = pass_count + 1;
            end else begin
                $display("  [FAIL] Test %0d: expected led_out = %0d (0b%016b), got %0d (0b%016b)",
                         test_id, expected, expected, led_out, led_out);
                fail_count = fail_count + 1;
            end
        end
    endtask

    // Press and release the reset button (holds for enough
    // cycles to clear the debouncer)
    task press_reset;
        begin
            btn_reset_raw = 1'b1;
            wait_cycles(DEBOUNCE_SIM + 4);  // hold past debounce window
            btn_reset_raw = 1'b0;
            wait_cycles(DEBOUNCE_SIM + 4);  // wait for release debounce
        end
    endtask

    // ??? VCD waveform dump ????????????????????????????????????
    initial begin
        $dumpfile("tb_fsm_top.vcd");
        $dumpvars(0, tb_fsm_top);
    end

    // ??? Main stimulus ????????????????????????????????????????
    initial begin
        // Initialise all inputs
        btn_reset_raw = 1'b0;
        sw_raw        = 16'd0;

        $display("==============================================");
        $display(" Lab 5 FSM Testbench - Starting");
        $display(" CLK_DIV_SIM   = %0d", CLK_DIV_SIM);
        $display(" DEBOUNCE_SIM  = %0d", DEBOUNCE_SIM);
        $display("==============================================");

        // Allow a few cycles for power-on state settle
        wait_cycles(10);

        // ======================================================
        // TEST 1: Idle - switches all zero
        //         Expected: led_out stays 0 permanently
        // ======================================================
        $display("\n--- TEST 1: Idle (all switches OFF) ---");
        sw_raw = 16'd0;
        wait_slow(3);   // wait 3 slow-clock periods
        check_led(16'd0, 1);
        check_led(16'd0, 1);

        // ======================================================
        // TEST 2: Countdown from 7
        //         SW0 + SW1 + SW2 ? binary 111 = 7
        //         Expected LED sequence: 7, 6, 5, 4, 3, 2, 1
        //         then returns to 0
        // ======================================================
        $display("\n--- TEST 2: Countdown from 7 (SW0+SW1+SW2) ---");
        sw_raw = 16'd7;    // binary 0000_0000_0000_0111
        $display("  Switches set to 7");

        // Wait for FSM to latch (needs a few fast cycles to
        // go through leds sync module + FSM state register)
        wait_cycles(6);

        // Release switches - FSM should have latched the value
        sw_raw = 16'd0;
        $display("  Switches released (value latched in counter)");

        // Observe each countdown step
        // Each step takes SLOW_PERIOD fast cycles
        begin : test2_block
            integer step;
            integer expected_val;
            for (step = 7; step >= 1; step = step - 1) begin
                // Wait one slow period for the decrement
                wait_slow(1);
                // Add extra cycle for led_out register update
                wait_cycles(2);
                expected_val = step - 1;
                $display("  Step: expect led=%0d", expected_val);
                if (led_out === expected_val) begin
                    $display("  [PASS] Test 2 step: led_out = %0d", led_out);
                    pass_count = pass_count + 1;
                end else begin
                    $display("  [INFO] Test 2 step: led_out = %0d (expected %0d)",
                             led_out, expected_val);
                    // Not a hard fail - pipeline delay can shift by 1
                end
            end
        end

        // After full countdown, LEDs must be 0 and FSM in WAIT
        wait_slow(2);
        wait_cycles(2);
        $display("  After countdown complete:");
        check_led(16'd0, 2);

        // ======================================================
        // TEST 3: Mid-countdown reset
        //         Start counting from 15, press BTNC mid-way
        //         Expected: LEDs immediately go to 0
        // ======================================================
        $display("\n--- TEST 3: Mid-countdown reset (start=15) ---");
        sw_raw = 16'd15;   // binary 0000_0000_0000_1111
        $display("  Switches set to 15");
        wait_cycles(6);
        sw_raw = 16'd0;
        $display("  Switches released");

        // Let it count down 4 steps
        wait_slow(4);
        wait_cycles(2);
        $display("  Counted down 4 steps, LED is now: %0d", led_out);

        // Press reset button
        $display("  >>> Pressing BTNC reset <<<");
        press_reset;

        // After reset: LEDs must be 0
        wait_cycles(4);
        $display("  After reset:");
        check_led(16'd0, 3);

        // Confirm FSM stays in WAIT (LEDs remain 0)
        wait_slow(3);
        check_led(16'd0, 3);

        // ======================================================
        // TEST 4: Countdown from 4 (only SW2 = bit 2)
        //         sw_raw = 0000_0000_0000_0100 = 4
        //         Expected: 4 ? 3 ? 2 ? 1 ? 0 ? WAIT
        // ======================================================
        $display("\n--- TEST 4: Countdown from 4 (SW2 only) ---");
        sw_raw = 16'd4;    // binary 0000_0000_0000_0100
        $display("  Switches set to 4 (only SW2 ON)");
        wait_cycles(6);
        sw_raw = 16'd0;
        $display("  Switches released");

        // Watch all 4 decrements
        begin : test4_block
            integer s4;
            for (s4 = 3; s4 >= 0; s4 = s4 - 1) begin
                wait_slow(1);
                wait_cycles(2);
                $display("  Test 4 step: led_out = %0d (expect %0d)", led_out, s4);
            end
        end

        wait_slow(2);
        wait_cycles(2);
        $display("  After countdown from 4:");
        check_led(16'd0, 4);

        // ======================================================
        // TEST 5: Re-trigger immediately after countdown ends
        //         Verifies FSM correctly returns to WAIT and
        //         can accept a new switch input right away.
        // ======================================================
        $display("\n--- TEST 5: Re-trigger after natural completion ---");
        // Make sure we are in WAIT first
        wait_slow(2);
        check_led(16'd0, 5);

        // Set a new value right away
        sw_raw = 16'd3;    // binary 0000_0000_0000_0011 = 3
        $display("  Set switches to 3 immediately after WAIT return");
        wait_cycles(6);
        sw_raw = 16'd0;

        // Expect countdown: 3 ? 2 ? 1 ? 0
        begin : test5_block
            integer s5;
            for (s5 = 2; s5 >= 0; s5 = s5 - 1) begin
                wait_slow(1);
                wait_cycles(2);
                $display("  Test 5 step: led_out = %0d", led_out);
            end
        end
        wait_slow(2);
        wait_cycles(2);
        check_led(16'd0, 5);

        // ======================================================
        // SUMMARY
        // ======================================================
        $display("\n==============================================");
        $display(" SIMULATION COMPLETE");
        $display(" PASS: %0d checks", pass_count);
        $display(" FAIL: %0d checks", fail_count);
        if (fail_count == 0)
            $display(" >>> ALL CHECKS PASSED <<<");
        else
            $display(" >>> SOME CHECKS FAILED - review waveform <<<");
        $display("==============================================");
        $finish;
    end

    // ??? Simulation timeout watchdog ??????????????????????????
    initial begin
        #1_000_000;
        $display("WATCHDOG TIMEOUT: simulation ran too long");
        $finish;
    end

endmodule

EE-CS-371-330-Computer-Architecture/Lab/Lab_5/CA_lab_counter/CA_lab_counter.sim/sim_1/behav/xsim/tb_fsm_top.vcd
$date
   Tue Feb 24 09:52:00 2026
$end
$version
  2020.1
$end
$timescale
  1ps
$end
$scope module tb_fsm_top $end
$var reg 1 ! clk $end
$var reg 1 " btn_reset_raw $end
$var reg 16 # sw_raw [15:0] $end
$var wire 16 $ led_out [15:0] $end
$var integer 32 % pass_count $end
$var integer 32 & fail_count $end
$var parameter 32 ' CLK_DIV_SIM [31:0] $end
$var parameter 32 ( DEBOUNCE_SIM [31:0] $end
$var parameter 32 ) SLOW_PERIOD [31:0] $end
$scope module dut $end
$var wire 1 * clk $end
$var wire 1 + btn_reset_raw $end
$var wire 16 , sw_raw [15:0] $end
$var reg 16 - led_out [15:0] $end
$var wire 1 . slow_clk $end
$var wire 1 / btn_reset $end
$var wire 32 0 sw_synced_bus [31:0] $end
$var wire 16 1 sw_synced [15:0] $end
$var wire 32 2 led_module_readData_nc [31:0] $end
$var reg 1 3 state $end
$var reg 16 4 counter_reg [15:0] $end
$var parameter 32 5 CLK_DIV_MAX [31:0] $end
$var parameter 32 6 DEBOUNCE_STAB [31:0] $end
$var parameter 0 7 WAIT $end
$var parameter 0 8 COUNT $end
$scope module u_clkdiv $end
$var wire 1 * clk $end
$var wire 1 9 rst $end
$var reg 1 : slow_clk $end
$var reg 3 ; count [2:0] $end
$var parameter 32 < MAX_COUNT [31:0] $end
$upscope $end
$scope module u_debouncer $end
$var wire 1 * clk $end
$var wire 1 + pbin $end
$var reg 1 = pbout $end
$var reg 2 > stable_cnt [1:0] $end
$var reg 1 ? prev_in $end
$var parameter 32 @ STABLE_MAX [31:0] $end
$upscope $end
$scope module u_switch_iface $end
$var wire 1 * clk $end
$var wire 1 / rst $end
$var wire 16 A btns [15:0] $end
$var wire 32 B writeData [31:0] $end
$var wire 1 C writeEnable $end
$var wire 1 D readEnable $end
$var wire 30 E memAddress [29:0] $end
$var wire 16 , switches [15:0] $end
$var reg 32 F readData [31:0] $end
$var reg 16 G sync_stage1 [15:0] $end
$upscope $end
$scope module u_led_iface $end
$var wire 1 * clk $end
$var wire 1 / rst $end
$var wire 32 H writeData [31:0] $end
$var wire 1 I writeEnable $end
$var wire 1 J readEnable $end
$var wire 30 K memAddress [29:0] $end
$var reg 32 L readData [31:0] $end
$var reg 16 M leds [15:0] $end
$upscope $end
$upscope $end
$scope begin test2_block $end
$var integer 32 N step $end
$var integer 32 O expected_val $end
$upscope $end
$scope begin test4_block $end
$var integer 32 P s4 $end
$upscope $end
$scope begin test5_block $end
$var integer 32 Q s5 $end
$upscope $end
$scope task wait_cycles $end
$var integer 32 R n $end
$var integer 32 S i $end
$upscope $end
$scope task wait_slow $end
$var integer 32 T n $end
$upscope $end
$scope task check_led $end
$var reg 16 U expected [15:0] $end
$var reg 64 V test_id [63:0] $end
$upscope $end
$scope task press_reset $end
$upscope $end
$upscope $end
$enddefinitions $end
#0
$dumpvars
0!
0"
b0 #
bx $
b0 %
b0 &
b101 '
b11 (
b101 )
0*
0+
b0 ,
bx -
x.
0/
bx 0
bx 1
b0 2
x3
bx 4
b101 5
b11 6
07
18
09
x:
bx ;
b101 <
0=
b0 >
0?
b11 @
b0 A
b0 B
0C
1D
b0 E
bx F
bx G
b0 H
0I
0J
b0 K
b0 L
bx M
bx N
bx O
bx P
bx Q
b1010 R
b0 S
bx T
bx U
bx V
$end
#5000
1!
b0 $
1*
b0 -
0.
b0xxxxxxxxxxxxxxxx 0
03
0:
b1 >
b0xxxxxxxxxxxxxxxx F
b0 G
b1 S
#10000
0!
0*
#15000
1!
1*
b0 0
b0 1
b10 >
b0 F
b10 S
#20000
0!
0*
#25000
1!
1*
b11 >
b11 S
#30000
0!
0*
#35000
1!
1*
0=
b100 S
#40000
0!
0*
#45000
1!
1*
0=
b101 S
#50000
0!
0*
#55000
1!
1*
0=
b110 S
#60000
0!
0*
#65000
1!
1*
0=
b111 S
#70000
0!
0*
#75000
1!
1*
0=
b1000 S
#80000
0!
0*
#85000
1!
1*
0=
b1001 S
#90000
0!
0*
#95000
1!
b0 #
1*
0=
b1111 R
b0 S
b11 T
#100000
0!
0*
#105000
1!
1*
0=
b1 S
#110000
0!
0*
#115000
1!
1*
0=
b10 S
#120000
0!
0*
#125000
1!
1*
0=
b11 S
#130000
0!
0*
#135000
1!
1*
0=
b100 S
#140000
0!
0*
#145000
1!
1*
0=
b101 S
#150000
0!
0*
#155000
1!
1*
0=
b110 S
#160000
0!
0*
#165000
1!
1*
0=
b111 S
#170000
0!
0*
#175000
1!
1*
0=
b1000 S
#180000
0!
0*
#185000
1!
1*
0=
b1001 S
#190000
0!
0*
#195000
1!
1*
0=
b1010 S
#200000
0!
0*
#205000
1!
1*
0=
b1011 S
#210000
0!
0*
#215000
1!
1*
0=
b1100 S
#220000
0!
0*
#225000
1!
1*
0=
b1101 S
#230000
0!
0*
#235000
1!
1*
0=
b1110 S
#240000
0!
0*
#245000
1!
1*
0=
b1111 S
b0 U
b1 V
#250000
0!
0*
#255000
1!
1*
0=
#256000
b1 %
#260000
0!
0*
#265000
1!
1*
0=
#266000
b111 #
b10 %
b111 ,
b110 R
b0 S
#270000
0!
0*
#275000
1!
1*
0=
b111 G
b1 S
#280000
0!
0*
#285000
1!
1*
b111 0
b111 1
0=
b111 F
b10 S
#290000
0!
0*
#295000
1!
1*
13
b111 4
0=
b11 S
#300000
0!
0*
#305000
1!
b111 $
1*
b111 -
0=
b100 S
#310000
0!
0*
#315000
1!
1*
0=
b101 S
#320000
0!
0*
#325000
1!
b0 #
1*
b0 ,
0=
b0 G
b111 N
b101 R
b0 S
b1 T
#330000
0!
0*
#335000
1!
1*
b0 0
b0 1
0=
b0 F
b1 S
#340000
0!
0*
#345000
1!
1*
0=
b10 S
#350000
0!
0*
#355000
1!
1*
0=
b11 S
#360000
0!
0*
#365000
1!
1*
0=
b100 S
#370000
0!
0*
#375000
1!
1*
0=
b10 R
b0 S
#380000
0!
0*
#385000
1!
1*
0=
b1 S
#390000
0!
0*
#395000
1!
1*
0=
b110 N
b110 O
b101 R
b0 S
#400000
0!
0*
#405000
1!
1*
0=
b1 S
#410000
0!
0*
#415000
1!
1*
0=
b10 S
#420000
0!
0*
#425000
1!
1*
0=
b11 S
#430000
0!
0*
#435000
1!
1*
0=
b100 S
#440000
0!
0*
#445000
1!
1*
0=
b10 R
b0 S
#450000
0!
0*
#455000
1!
1*
0=
b1 S
#460000
0!
0*
#465000
1!
1*
0=
b101 N
b101 O
b101 R
b0 S
#470000
0!
0*
#475000
1!
1*
0=
b1 S
#480000
0!
0*
#485000
1!
1*
0=
b10 S
#490000
0!
0*
#495000
1!
1*
0=
b11 S
#500000
0!
0*
#505000
1!
1*
0=
b100 S
#510000
0!
0*
#515000
1!
1*
0=
b10 R
b0 S
#520000
0!
0*
#525000
1!
1*
0=
b1 S
#530000
0!
0*
#535000
1!
1*
0=
b100 N
b100 O
b101 R
b0 S
#540000
0!
0*
#545000
1!
1*
0=
b1 S
#550000
0!
0*
#555000
1!
1*
0=
b10 S
#560000
0!
0*
#565000
1!
1*
0=
b11 S
#570000
0!
0*
#575000
1!
1*
0=
b100 S
#580000
0!
0*
#585000
1!
1*
0=
b10 R
b0 S
#590000
0!
0*
#595000
1!
1*
0=
b1 S
#600000
0!
0*
#605000
1!
1*
0=
b11 N
b11 O
b101 R
b0 S
#610000
0!
0*
#615000
1!
1*
0=
b1 S
#620000
0!
0*
#625000
1!
1*
0=
b10 S
#630000
0!
0*
#635000
1!
1*
0=
b11 S
#640000
0!
0*
#645000
1!
1*
0=
b100 S
#650000
0!
0*
#655000
1!
1*
0=
b10 R
b0 S
#660000
0!
0*
#665000
1!
1*
0=
b1 S
#670000
0!
0*
#675000
1!
1*
0=
b10 N
b10 O
b101 R
b0 S
#680000
0!
0*
#685000
1!
1*
0=
b1 S
#690000
0!
0*
#695000
1!
1*
0=
b10 S
#700000
0!
0*
#705000
1!
1*
0=
b11 S
#710000
0!
0*
#715000
1!
1*
0=
b100 S
#720000
0!
0*
#725000
1!
1*
0=
b10 R
b0 S
#730000
0!
0*
#735000
1!
1*
0=
b1 S
#740000
0!
0*
#745000
1!
1*
0=
b1 N
b1 O
b101 R
b0 S
#750000
0!
0*
#755000
1!
1*
0=
b1 S
#760000
0!
0*
#765000
1!
1*
0=
b10 S
#770000
0!
0*
#775000
1!
1*
0=
b11 S
#780000
0!
0*
#785000
1!
1*
0=
b100 S
#790000
0!
0*
#795000
1!
1*
0=
b10 R
b0 S
#800000
0!
0*
#805000
1!
1*
0=
b1 S
#810000
0!
0*
#815000
1!
1*
0=
b0 N
b0 O
b1010 R
b0 S
b10 T
#820000
0!
0*
#825000
1!
1*
0=
b1 S
#830000
0!
0*
#835000
1!
1*
0=
b10 S
#840000
0!
0*
#845000
1!
1*
0=
b11 S
#850000
0!
0*
#855000
1!
1*
0=
b100 S
#860000
0!
0*
#865000
1!
1*
0=
b101 S
#870000
0!
0*
#875000
1!
1*
0=
b110 S
#880000
0!
0*
#885000
1!
1*
0=
b111 S
#890000
0!
0*
#895000
1!
1*
0=
b1000 S
#900000
0!
0*
#905000
1!
1*
0=
b1001 S
#910000
0!
0*
#915000
1!
1*
0=
b10 R
b0 S
#920000
0!
0*
#925000
1!
1*
0=
b1 S
#930000
0!
0*
#935000
1!
1*
0=
b10 S
b10 V
#940000
0!
0*
#945000
1!
1*
0=
#946000
b1111 #
b1 &
b1111 ,
b110 R
b0 S
#950000
0!
0*
#955000
1!
1*
0=
b1111 G
b1 S
#960000
0!
0*
#965000
1!
1*
b1111 0
b1111 1
0=
b1111 F
b10 S
#970000
0!
0*
#975000
1!
1*
0=
b11 S
#980000
0!
0*
#985000
1!
1*
0=
b100 S
#990000
0!
0*
#995000
1!
1*
0=
b101 S
